.DS_Store
superfunctions/__init__.py
superfunctions/superfunctions.py
superfunctions-0.1.3.dist-info/METADATA
superfunctions-0.1.3.dist-info/WHEEL
superfunctions-0.1.3.dist-info/top_level.txt
superfunctions-0.1.3.dist-info/RECORD
