Metadata-Version: 2.1
Name: superfunctions
Version: 0.1.3
Summary: Metafunctions with less repetition
Home-page: UNKNOWN
Author: Youssef
Author-email: youssef.avx@gmail.com
License: UNKNOWN
Keywords: python,first package
Platform: UNKNOWN
Classifier: Development Status :: 2 - Pre-Alpha
Classifier: Intended Audience :: Developers
Classifier: Programming Language :: Python :: 2
Classifier: Programming Language :: Python :: 3
Classifier: Operating System :: MacOS :: MacOS X
Classifier: Operating System :: Microsoft :: Windows
Requires-Dist: metafunctions
Requires-Dist: dis
